README.md
setup.py
demoji/__init__.py
demoji/apiresponse.py
demoji/discordemoji.py
demoji/errors.py
demoji/requestmanager.py
demojipy.egg-info/PKG-INFO
demojipy.egg-info/SOURCES.txt
demojipy.egg-info/dependency_links.txt
demojipy.egg-info/requires.txt
demojipy.egg-info/top_level.txt