Metadata-Version: 2.1
Name: demojipy
Version: 3.0.0
Summary: Python Wrapper for DiscordEmoji API
Home-page: https://github.com/Algueem/DiscordEmojiPy
Author: Algueem
License: MIT
Keywords: pydemoji,discordemoji
Platform: UNKNOWN
Classifier: Development Status :: 5 - Production/Stable
Classifier: Programming Language :: Python :: 3.6
Classifier: License :: OSI Approved :: MIT License
Classifier: Operating System :: OS Independent
